pytest_mark_count/__init__.py
pytest_mark_count/plugin.py
pytest_mark_count/py.typed
pytest_mark_count/version.py
pytest_mark_count-0.5.1.dist-info/LICENSE
pytest_mark_count-0.5.1.dist-info/METADATA
pytest_mark_count-0.5.1.dist-info/WHEEL
pytest_mark_count-0.5.1.dist-info/entry_points.txt
pytest_mark_count-0.5.1.dist-info/top_level.txt
pytest_mark_count-0.5.1.dist-info/RECORD
